ApiFK_frekassa/__init__.py
ApiFK_frekassa/api.py
ApiFK_frekassa/api_base.py
ApiFK_frekassa/utils.py
ApiFK_frekassa/models/__init__.py
ApiFK_frekassa/models/balance.py
ApiFK_frekassa/type/__init__.py
ApiFK_frekassa/type/currencies.py
ApiFK_frekassa/type/languages.py
ApiFK_frekassa/type/order_statuses.py
ApiFK_frekassa/type/payment_methods.py
ApiFK_frekassa-0.2.dist-info/LICENSE
ApiFK_frekassa-0.2.dist-info/METADATA
ApiFK_frekassa-0.2.dist-info/WHEEL
ApiFK_frekassa-0.2.dist-info/top_level.txt
ApiFK_frekassa-0.2.dist-info/RECORD
